[
  {
    "id": 1,
    "forename": "",
    "surname": "Total",
    "contractStartDate": "",
    "contractEndDate": "",
    "DOB": "",
    "dateBought": "various",
    "rating": 0,
    "notes": "total"
  },
  {
    "id": 2,
    "forename": "Victor",
    "surname": "Adebayejo",
    "contractStartDate": "27/01/2023",
    "contractEndDate": "30/06/2026",
    "DOB": "12/01/1998",
    "dateBought": "26/01/2023",
    "rating": 0,
    "notes": "Gone"
  },
  {
    "id": 3,
    "forename": "Jack",
    "surname": "Bonham",
    "contractStartDate": "14/01/2026",
    "contractEndDate": "20/06/2027",
    "DOB": "14/09/1993",
    "dateBought": "14/01/2026",
    "rating": 0,
    "notes": "Squad"
  },
  {
    "id": 4,
    "forename": "Nathan",
    "surname": "Broom",
    "contractStartDate": "22/07/2025",
    "contractEndDate": "30/06/2026",
    "DOB": "03/01/2022",
    "dateBought": "22/07/2025",
    "rating": 0,
    "notes": "On loan"
  },
  {
    "id": 5,
    "forename": "Cyrus",
    "surname": "Christie",
    "contractStartDate": "31/08/2025",
    "contractEndDate": "30/06/2026",
    "DOB": "30/09/1992",
    "dateBought": "",
    "rating": 0,
    "notes": "Squad"
  },
  {
    "id": 6,
    "forename": "Maxwell",
    "surname": "Conway",
    "contractStartDate": "24/05/2023",
    "contractEndDate": "30/06/2029",
    "DOB": "05/09/2003",
    "dateBought": "",
    "rating": 0,
    "notes": "Squad"
  },
  {
    "id": 7,
    "forename": "Joshua",
    "surname": "Dacre-Cogley",
    "contractStartDate": "01/07/2023",
    "contractEndDate": "30/06/2026",
    "DOB": "12/03/1996",
    "dateBought": "",
    "rating": 0,
    "notes": "Gone"
  },
  {
    "id": 8,
    "forename": "Sam",
    "surname": "Dalby",
    "contractStartDate": "01/07/2025",
    "contractEndDate": "30/06/2029",
    "DOB": "09/12/1999",
    "dateBought": "",
    "rating": 0,
    "notes": "Squad"
  },
  {
    "id": 9,
    "forename": "Kyle",
    "surname": "Dempsey",
    "contractStartDate": "23/06/2023",
    "contractEndDate": "30/06/2026",
    "DOB": "17/09/1995",
    "dateBought": "",
    "rating": 0,
    "notes": "Squad"
  },
  {
    "id": 10,
    "forename": "Ethan",
    "surname": "Erhahon",
    "contractStartDate": "25/07/2025",
    "contractEndDate": "30/06/2029",
    "DOB": "09/05/2001",
    "dateBought": "",
    "rating": 0,
    "notes": "Squad"
  },
  {
    "id": 11,
    "forename": "Chris",
    "surname": "Forino",
    "contractStartDate": "01/07/2024",
    "contractEndDate": "30/06/2027",
    "DOB": "26/04/2000",
    "dateBought": "",
    "rating": 0,
    "notes": "Squad"
  },
  {
    "id": 12,
    "forename": "Will",
    "surname": "Forrester",
    "contractStartDate": "04/07/2023",
    "contractEndDate": "30/06/2026",
    "DOB": "29/06/2001",
    "dateBought": "",
    "rating": 0,
    "notes": "Gone"
  },
  {
    "id": 13,
    "forename": "Thierry",
    "surname": "Gale",
    "contractStartDate": "04/07/2025",
    "contractEndDate": "3006/2029",
    "DOB": "01/05/2002",
    "dateBought": "",
    "rating": 0,
    "notes": "Squad"
  },
  {
    "id": 14,
    "forename": "David",
    "surname": "Harrington",
    "contractStartDate": "14/01/2025",
    "contractEndDate": "30/06/2028",
    "DOB": "01/07/2000",
    "dateBought": "",
    "rating": 0,
    "notes": "Squad"
  },
  {
    "id": 15,
    "forename": "Luke",
    "surname": "Huchinson",
    "contractStartDate": "01/07/2025",
    "contractEndDate": "30/06/2027",
    "DOB": "01/09/2002",
    "dateBought": "",
    "rating": 0,
    "notes": "On loan"
  },
  {
    "id": 16,
    "forename": "George",
    "surname": "Johnston",
    "contractStartDate": "31/07/2023",
    "contractEndDate": "30/06/2026",
    "DOB": "01/09/1998",
    "dateBought": "",
    "rating": 0,
    "notes": "Squad"
  },
  {
    "id": 17,
    "forename": "John",
    "surname": "McAtee",
    "contractStartDate": "09/08/2024",
    "contractEndDate": "30/06/2026",
    "DOB": "23/07/1999",
    "dateBought": "",
    "rating": 0,
    "notes": "Squad"
  },
  {
    "id": 18,
    "forename": "Tyler",
    "surname": "Miller",
    "contractStartDate": "11/08/2025",
    "contractEndDate": "30/06/2026",
    "DOB": "12/03/1993",
    "dateBought": "",
    "rating": 0,
    "notes": "Gone"
  },
  {
    "id": 19,
    "forename": "Aaron",
    "surname": "Morley",
    "contractStartDate": "27/12/2023",
    "contractEndDate": "30/06/2027",
    "DOB": "27/02/2000",
    "dateBought": "",
    "rating": 0,
    "notes": "Gone"
  },
  {
    "id": 20,
    "forename": "Jordi",
    "surname": "Osei-Tutu",
    "contractStartDate": "07/08/2024",
    "contractEndDate": "30/06/2026",
    "DOB": "02/10/1998",
    "dateBought": "",
    "rating": 0,
    "notes": "Squad"
  },
  {
    "id": 40,
    "forename": "Rubin",
    "surname": "Rodrigues",
    "contractStartDate": "30/01/2026",
    "contractEndDate": "30/06/2027",
    "DOB": "02/08/1996",
    "dateBought": "",
    "rating": 0,
    "notes": "Squad"
  },
  {
    "id": 21,
    "forename": "Joel",
    "surname": "Randell",
    "contractStartDate": "09/01/2025",
    "contractEndDate": "30/06/2028",
    "DOB": "29/10/1999",
    "dateBought": "",
    "rating": 0,
    "notes": "On loan"
  },
  {
    "id": 22,
    "forename": "Joshua",
    "surname": "Sheehan",
    "contractStartDate": "01/07/2021",
    "contractEndDate": "30/06/2027",
    "DOB": "30/03/1995",
    "dateBought": "",
    "rating": 0,
    "notes": "Squad"
  },
  {
    "id": 23,
    "forename": "Xavier",
    "surname": "Simons",
    "contractStartDate": "01/07/2025",
    "contractEndDate": "30/06/2029",
    "DOB": "20/02/2003",
    "dateBought": "",
    "rating": 0,
    "notes": "Squad"
  },
  {
    "id": 24,
    "forename": "Richard",
    "surname": "Taylor",
    "contractStartDate": "01/07/2025",
    "contractEndDate": "30/06/2028",
    "DOB": "02/10/2000",
    "dateBought": "",
    "rating": 0,
    "notes": "Squad"
  },
  {
    "id": 25,
    "forename": "Lewis",
    "surname": "Temple",
    "contractStartDate": "01/01/2026",
    "contractEndDate": "20/06/2028",
    "DOB": "11/06/2005",
    "dateBought": "",
    "rating": 0,
    "notes": "Squad"
  },
  {
    "id": 26,
    "forename": "Eoin",
    "surname": "Toal",
    "contractStartDate": "04/03/2024",
    "contractEndDate": "30/06/2027",
    "DOB": "15/02/1999",
    "dateBought": "",
    "rating": 0,
    "notes": "Squad"
  },
  {
    "id": 27,
    "forename": "Charlie",
    "surname": "Warren",
    "contractStartDate": "01/07/2025",
    "contractEndDate": "30/06/2027",
    "DOB": "24/01/2004",
    "dateBought": "",
    "rating": 0,
    "notes": "On loan"
  },
  {
    "id": 37,
    "forename": "Rob",
    "surname": "Apter",
    "contractStartDate": "25/01/2026",
    "contractEndDate": "30/06/2026",
    "DOB": "23/04/2003",
    "dateBought": "",
    "rating": 0,
    "notes": "Loan in"
  },
  {
    "id": 38,
    "forename": "Corey",
    "surname": "Blackett-Taylor",
    "contractStartDate": "28/01/2026",
    "contractEndDate": "330/06/2026",
    "DOB": "23/09/1997",
    "dateBought": "",
    "rating": 0,
    "notes": "Loan in"
  },
  {
    "id": 29,
    "forename": "Teddy",
    "surname": "Sharman-Lowe",
    "contractStartDate": "01/07/2025",
    "contractEndDate": "30/06/2026",
    "DOB": "30/03/2003",
    "dateBought": "",
    "rating": 0,
    "notes": "Gone"
  },
  {
    "id": 30,
    "forename": "Mason",
    "surname": "Burstow",
    "contractStartDate": "28/07/2025",
    "contractEndDate": "30/06/2026",
    "DOB": "04/08/2003",
    "dateBought": "",
    "rating": 0,
    "notes": "Loan in"
  },
  {
    "id": 31,
    "forename": "Ibrahim",
    "surname": "Cissoko",
    "contractStartDate": "28/07/2025",
    "contractEndDate": "30/06/2026",
    "DOB": "26/03/2003",
    "dateBought": "",
    "rating": 0,
    "notes": "Loan in"
  },
  {
    "id": 39,
    "forename": "Marcus",
    "surname": "Forss",
    "contractStartDate": "30/08/2025",
    "contractEndDate": "30/06/2026",
    "DOB": "18/06/1999",
    "dateBought": "",
    "rating": 0,
    "notes": "Loan in"
  },
  {
    "id": 39,
    "forename": "Johnny",
    "surname": "Kenny",
    "contractStartDate": "02/02/2026",
    "contractEndDate": "30/06/2026",
    "DOB": "06/06/2003",
    "dateBought": "",
    "rating": 0,
    "notes": "Loan in"
  },
  {
    "id": 48,
    "forename": "Amario",
    "surname": "Cozier-Duberry",
    "contractStartDate": "05/07/2025",
    "contractEndDate": "30/06/2026",
    "DOB": "29/05/2005",
    "dateBought": "",
    "rating": 0,
    "notes": "Loan in"
  },
  {
    "id": 33,
    "forename": "Sonny",
    "surname": "Sharples-Ahmed",
    "contractStartDate": "13/04/2023",
    "contractEndDate": "30/06/2025",
    "DOB": "24/03/2005",
    "dateBought": "",
    "rating": 0,
    "notes": "Squad"
  },
  {
    "id": 34,
    "forename": "Sam",
    "surname": "Inwood",
    "contractStartDate": "29/08/2025",
    "contractEndDate": "30/06/2028",
    "DOB": "17/08/2005",
    "dateBought": "",
    "rating": 0,
    "notes": "On loan"
  },
  {
    "id": 38,
    "forename": "Carlos",
    "surname": "Mendes-Gomes",
    "contractStartDate": "24/07/2023",
    "contractEndDate": "30/06/2026",
    "DOB": "14/11/1998",
    "dateBought": "",
    "rating": 0,
    "notes": "On loan"
  },
  {
    "id": 36,
    "forename": "Szabolcs",
    "surname": "Schon",
    "contractStartDate": "02/08/2024",
    "contractEndDate": "30/06/2027",
    "DOB": "27/09/2000",
    "dateBought": "",
    "rating": 0,
    "notes": "On loan"
  },
  {
    "id": 44,
    "forename": "Klaidi",
    "surname": "Lolos",
    "contractStartDate": "27/06/2024",
    "contractEndDate": "31/07/2025",
    "DOB": "06/10/2000",
    "dateBought": "",
    "rating": 0,
    "notes": "On loan"
  },
  {
    "id": 45,
    "forename": "Luke",
    "surname": "Southwood",
    "contractStartDate": "01/07/2024",
    "contractEndDate": "05/07/2025",
    "DOB": "06/12/1997",
    "dateBought": "",
    "rating": 0,
    "notes": "Gone"
  },
  {
    "id": 46,
    "forename": "Geroge",
    "surname": "Thomason",
    "contractStartDate": "19/09/2024",
    "contractEndDate": "30/06/2028",
    "DOB": "12/01/2001",
    "dateBought": "",
    "rating": 0,
    "notes": "Gone"
  },
  {
    "id": 47,
    "forename": "Konda",
    "surname": "Nlundulu",
    "contractStartDate": "23/06/2023",
    "contractEndDate": "30/06/2026",
    "DOB": "05/02/1999",
    "dateBought": "",
    "rating": 0,
    "notes": "Gone"
  }
]